datapizza/modules/rerankers/cohere/__init__.py
datapizza/modules/rerankers/cohere/cohere_reranker.py
datapizza_ai_rerankers_cohere-0.0.4.dist-info/METADATA
datapizza_ai_rerankers_cohere-0.0.4.dist-info/WHEEL
datapizza_ai_rerankers_cohere-0.0.4.dist-info/RECORD
